em1l10/__init__.py
em1l10/courses.py
em1l10-0.1.0.dist-info/METADATA
em1l10-0.1.0.dist-info/WHEEL
em1l10-0.1.0.dist-info/top_level.txt
em1l10-0.1.0.dist-info/RECORD
