Metadata-Version: 2.1
Name: em1l10
Version: 0.1.0
Summary: First Package
Home-page: https://google.es
Author: Emilio Arteaga
